minkit/__init__.py
minkit/version.py
minkit/backends/__init__.py
minkit/backends/aop.py
minkit/backends/arrays.py
minkit/backends/autocode.py
minkit/backends/core.py
minkit/backends/cpu.py
minkit/backends/gpu.py
minkit/backends/gpu_cache.py
minkit/backends/gpu_core.py
minkit/backends/gpu_functions.py
minkit/backends/gsl_api.py
minkit/backends/src/gpu/functions_by_element.c
minkit/backends/src/gpu/philox.c
minkit/backends/src/gpu/templates_1d.c
minkit/backends/src/gpu/templates_2d.c
minkit/backends/src/gpu/templates_rndm.c
minkit/backends/src/templates/evaluators.c
minkit/backends/src/templates/function.c
minkit/backends/src/templates/integral.c
minkit/backends/src/templates/numerical_integral.c
minkit/backends/src/templates/whole.c
minkit/backends/src/xml/Amoroso.xml
minkit/backends/src/xml/Argus.xml
minkit/backends/src/xml/Chebyshev.xml
minkit/backends/src/xml/CrystalBall.xml
minkit/backends/src/xml/ExpPoly.xml
minkit/backends/src/xml/Exponential.xml
minkit/backends/src/xml/Gaussian.xml
minkit/backends/src/xml/Landau.xml
minkit/backends/src/xml/Polynomial.xml
minkit/backends/src/xml/PowerLaw.xml
minkit/base/__init__.py
minkit/base/bindings.py
minkit/base/core.py
minkit/base/data_types.py
minkit/base/dependencies.py
minkit/base/exceptions.py
minkit/base/parameters.py
minkit/minimization/__init__.py
minkit/minimization/core.py
minkit/minimization/evaluators.py
minkit/minimization/fcns.py
minkit/minimization/minimizers.py
minkit/minimization/minuit_api.py
minkit/minimization/scipy_api.py
minkit/pdfs/__init__.py
minkit/pdfs/dataset.py
minkit/pdfs/pdf_core.py
minkit/pdfs/pdfs.py
minkit/utils/__init__.py
minkit/utils/core.py
minkit/utils/profile.py
minkit/utils/splot.py
minkit-0.0.0.dev1.dist-info/LICENSE.txt
minkit-0.0.0.dev1.dist-info/METADATA
minkit-0.0.0.dev1.dist-info/WHEEL
minkit-0.0.0.dev1.dist-info/top_level.txt
minkit-0.0.0.dev1.dist-info/RECORD
