Metadata-Version: 2.1
Name: minkit
Version: 0.0.0.dev1
Summary: Package to perform fits in both CPUs and GPUs
Home-page: UNKNOWN
Author: UNKNOWN
Author-email: UNKNOWN
License: UNKNOWN
Keywords: hep high energy physics fit pdf probability
Platform: UNKNOWN
Requires-Dist: iminuit (>=1.3)
Requires-Dist: numpy (>=1.17)
Requires-Dist: numdifftools (>=0.9.39)
Requires-Dist: scipy (>=1.3.2)
Requires-Dist: uncertainties (>=3.1.2)
